google_colab_tor_proxy/__init__.py
google_colab_tor_proxy/main.py
google_colab_tor_proxy-0.1.0.dist-info/METADATA
google_colab_tor_proxy-0.1.0.dist-info/WHEEL
google_colab_tor_proxy-0.1.0.dist-info/top_level.txt
google_colab_tor_proxy-0.1.0.dist-info/RECORD
