Metadata-Version: 2.1
Name: google_colab_tor_proxy
Version: 0.1.0
Summary: A tool for installing and configuring Tor and Privoxy.
Home-page: https://github.com/Yukendiran2002/google_colab_tor_proxy
Author: Yukendiran
Author-email: yukendiranjayachandiran@gmail.com
Classifier: Programming Language :: Python :: 3
Classifier: Operating System :: Unix
Requires-Python: >=3.6
